{
    "_gat":"1",
    "_ga":"GA1.2.1206298903.1487084315",
    "4Oaf_61d6_saltkey":"BrRjCtti",
    "4Oaf_61d6_lastvisit":"1487243132",
    "4Oaf_61d6_sendmail":"1",
    "sc_is_visitor_unique":"rx4760979.1487246734.59EE14AB0E1F4F41E428F72774BB01FB.11.9.7.6.5.4.3.3.3-4806808.1487234836.1.1.1.1.1.1.1.1.1",
    "__utmt":"1",
    "__utma":"142000562.1206298903.1487084315.1487240454.1487246188.10",
    "__utmb":"142000562.15.10.1487246188",
    "__utmc":"142000562",
    "__utmz":"142000562.1487084315.1.1.utmcsr=(direct)|utmccn=(direct)|utmcmd=(none)",
    "4Oaf_61d6_lastact":"1487246746%09member.php%09logging",
    "4Oaf_61d6_ulastactivity":"bd637fmT86fVcLZZ1MUqnq3H6eezvVMfXEuehodTgrRX7yo99Azc",
    "4Oaf_61d6_sid":"fU17S7",
    "4Oaf_61d6_auth":"26124OvfdJYjlZgUnCJYt3M4RZUItLfkyExRtUQjeiU%2F4pmh2ZXEjz346DXgS%2BlX4R8lBKOney4rUE%2Fu3aaFfTVL%2Bu4",
    "4Oaf_61d6_lastcheckfeed":"269641%7C1487246746",
    "4Oaf_61d6_checkfollow":"1",
    "4Oaf_61d6_lip":"183.149.225.164%2C1487246680"
}